{"id":"demo", "target":"gwswastesimulation","name":"Waste generation simulation","description":"Waste generation simulation.","start_time":1577836800000,"end_time":1609459200000,"timeout":120000,"status":"pending","user_id":"b6de5f00-215e-56a5-bb41-09b0d2f97bd7","speed":6000,"population":{"citizens":{"template":{"@gwsclass":"GWSEntity","type":"Citizen","@gwsgroups":["Human","Citizen"],"birth":-1,"@behaviours":[{"@gwsclass":"SendEntitySnapshotBehaviour","start":true,"id":"DISPLAY","entity_to_send_id":"<id>","duration":1,"nexts":["RAND_NUM1"]},{"@gwsclass":"GenerateRandomValueBehaviour","id":"RAND_NUM1","duration":1,"store_random_value_as":"hour","factor_to_multiply_random_value_with":12,"nexts":["RAND_NUM2"]},{"@gwsclass":"GenerateRandomValueBehaviour","id":"RAND_NUM2","duration":1,"store_random_value_as":"minute","factor_to_multiply_random_value_with":60,"nexts":["SET_HOUR"]},{"@gwsclass":"MathEntityPropertyBehaviour","id":"SET_HOUR","duration":1,"entity_to_operate_on_id":"<id>","property_to_modify":"hour","math_operator":"+","operand_value":7,"nexts":["WAIT"]},{"@gwsclass":"WaitUntilTimeBehaviour","id":"WAIT","wait_until_hour":"<hour>","wait_until_minute":"<minute>","wait_until_second":0,"wait_frequency":"day","duration":1,"nexts":["WASTE"]},{"@gwsclass":"GenerateWasteZamudioModelBehaviour","id":"WASTE","family_members":"TOTAL","duration":1,"nexts":["CHECK_ORGANIC"]},{"@gwsclass":"CompareEntityPropertyBehaviour","id":"CHECK_ORGANIC","duration":1,"entity_property_to_compare":"accumulated_organic","comparison_operator":">=","comparison_value":1,"nexts_if_true":["TRANSFER_ORGANIC"],"nexts_if_false":["CHECK_RESIDUAL"]},{"@gwsclass":"CompareEntityPropertyBehaviour","id":"CHECK_RESIDUAL","duration":1,"entity_property_to_compare":"accumulated_residual","comparison_operator":">=","comparison_value":1,"nexts_if_true":["TRANSFER_RESIDUAL"],"nexts_if_false":["CHECK_PAPER"]},{"@gwsclass":"CompareEntityPropertyBehaviour","id":"CHECK_PAPER","duration":1,"entity_property_to_compare":"accumulated_paper","comparison_operator":">=","comparison_value":1,"nexts_if_true":["TRANSFER_PAPER"],"nexts_if_false":["CHECK_PLASTIC"]},{"@gwsclass":"CompareEntityPropertyBehaviour","id":"CHECK_PLASTIC","duration":1,"entity_property_to_compare":"accumulated_plastic","comparison_operator":">=","comparison_value":1,"nexts_if_true":["TRANSFER_PLASTIC"],"nexts_if_false":["DISPLAY"]},{"@gwsclass":"TransactionBehaviour","duration":1,"id":"TRANSFER_ORGANIC","transaction_type":"WasteTransaction","transaction_data":{"emittedResources":[{"refResource":"ORGANIC"}]},"emitting_entity_id":"<id>","receiving_entity_id":"<routing_closest_ORGANIC>","nexts":["SET_ORGANIC_COLOR"]},{"@gwsclass":"SetEntityPropertyBehaviour","id":"SET_ORGANIC_COLOR","duration":1,"entity_to_set_id":"<routing_closest_ORGANIC>","properties":{"color":"chocolate"},"nexts":["DISPLAY_ORGANIC"]},{"@gwsclass":"SendEntitySnapshotBehaviour","id":"DISPLAY_ORGANIC","entity_to_send_id":"<routing_closest_ORGANIC>","duration":1,"nexts":["CHECK_RESIDUAL"]},{"@gwsclass":"TransactionBehaviour","duration":1,"id":"TRANSFER_RESIDUAL","transaction_type":"WasteTransaction","transaction_data":{"emittedResources":[{"refResource":"RESIDUAL"}]},"emitting_entity_id":"<id>","receiving_entity_id":"<routing_closest_RESIDUAL>","nexts":["SET_RESIDUAL_COLOR"]},{"@gwsclass":"SetEntityPropertyBehaviour","id":"SET_RESIDUAL_COLOR","duration":1,"entity_to_set_id":"<routing_closest_RESIDUAL>","properties":{"color":"gray"},"nexts":["DISPLAY_RESIDUAL"]},{"@gwsclass":"SendEntitySnapshotBehaviour","id":"DISPLAY_RESIDUAL","entity_to_send_id":"<routing_closest_RESIDUAL>","duration":1,"nexts":["CHECK_PAPER"]},{"@gwsclass":"TransactionBehaviour","duration":1,"id":"TRANSFER_PAPER","transaction_type":"WasteTransaction","transaction_data":{"emittedResources":[{"refResource":"PAPER"}]},"emitting_entity_id":"<id>","receiving_entity_id":"<routing_closest_PAPER>","nexts":["SET_PAPER_COLOR"]},{"@gwsclass":"SetEntityPropertyBehaviour","id":"SET_PAPER_COLOR","duration":1,"entity_to_set_id":"<routing_closest_PAPER>","properties":{"color":"blue"},"nexts":["DISPLAY_PAPER"]},{"@gwsclass":"SendEntitySnapshotBehaviour","id":"DISPLAY_PAPER","entity_to_send_id":"<routing_closest_PAPER>","duration":1,"nexts":["CHECK_PLASTIC"]},{"@gwsclass":"TransactionBehaviour","duration":1,"id":"TRANSFER_PLASTIC","transaction_type":"WasteTransaction","transaction_data":{"emittedResources":[{"refResource":"PLASTIC"}]},"emitting_entity_id":"<id>","receiving_entity_id":"<routing_closest_PLASTIC>","nexts":["SET_PLASTIC_COLOR"]},{"@gwsclass":"SetEntityPropertyBehaviour","id":"SET_PLASTIC_COLOR","duration":1,"entity_to_set_id":"<routing_closest_PLASTIC>","properties":{"color":"yellow"},"nexts":["DISPLAY_PLASTIC"]},{"@gwsclass":"SendEntitySnapshotBehaviour","id":"DISPLAY_PLASTIC","entity_to_send_id":"<routing_closest_PLASTIC>","duration":1,"nexts":["DISPLAY"]},{"@gwsclass":"StopEntityBehaviour","id":"STOP"}]},"datasources":[{"scenario_id":"9827b926-934d-429e-86f0-d0271be7ffa4-b6de5f00-215e-56a5-bb41-09","entity_type":"Citizen"}]},"container0":{"template":{"@gwsclass":"GWSEntity","type":"Container","radius":20,"@gwsgroups":["Container","Glass"],"@behaviours":[]},"datasources":[{"scenario_id":"9827b926-934d-429e-86f0-d0271be7ffa4-b6de5f00-215e-56a5-bb41-09","entity_type":"Glass"}]},"container1":{"template":{"@gwsclass":"GWSEntity","type":"Container","radius":20,"@gwsgroups":["Container","Organic"],"@behaviours":[]},"datasources":[{"scenario_id":"9827b926-934d-429e-86f0-d0271be7ffa4-b6de5f00-215e-56a5-bb41-09","entity_type":"Organic"}]},"container2":{"template":{"@gwsclass":"GWSEntity","type":"Container","radius":20,"@gwsgroups":["Container","Packaging"],"@behaviours":[]},"datasources":[{"scenario_id":"9827b926-934d-429e-86f0-d0271be7ffa4-b6de5f00-215e-56a5-bb41-09","entity_type":"Packaging"}]},"container3":{"template":{"@gwsclass":"GWSEntity","type":"Container","radius":20,"@gwsgroups":["Container","Paper"],"@behaviours":[]},"datasources":[{"scenario_id":"9827b926-934d-429e-86f0-d0271be7ffa4-b6de5f00-215e-56a5-bb41-09","entity_type":"Paper"}]},"container4":{"template":{"@gwsclass":"GWSEntity","type":"Container","radius":20,"@gwsgroups":["Container","Residual"],"@behaviours":[]},"datasources":[{"scenario_id":"9827b926-934d-429e-86f0-d0271be7ffa4-b6de5f00-215e-56a5-bb41-09","entity_type":"Residual"}]}}}
